{
  "properties": {
    "east": [
      true,
      false
    ],
    "north": [
      true,
      false
    ],
    "south": [
      true,
      false
    ],
    "waterlogged": [
      true,
      false
    ],
    "west": [
      true,
      false
    ]
  },
  "states": {
    "default": 15316,
    "15285": {
      "east": true,
      "north": true,
      "south": true,
      "waterlogged": true,
      "west": true
    },
    "15286": {
      "east": true,
      "north": true,
      "south": true,
      "waterlogged": true,
      "west": false
    },
    "15287": {
      "east": true,
      "north": true,
      "south": true,
      "waterlogged": false,
      "west": true
    },
    "15288": {
      "east": true,
      "north": true,
      "south": true,
      "waterlogged": false,
      "west": false
    },
    "15289": {
      "east": true,
      "north": true,
      "south": false,
      "waterlogged": true,
      "west": true
    },
    "15290": {
      "east": true,
      "north": true,
      "south": false,
      "waterlogged": true,
      "west": false
    },
    "15291": {
      "east": true,
      "north": true,
      "south": false,
      "waterlogged": false,
      "west": true
    },
    "15292": {
      "east": true,
      "north": true,
      "south": false,
      "waterlogged": false,
      "west": false
    },
    "15293": {
      "east": true,
      "north": false,
      "south": true,
      "waterlogged": true,
      "west": true
    },
    "15294": {
      "east": true,
      "north": false,
      "south": true,
      "waterlogged": true,
      "west": false
    },
    "15295": {
      "east": true,
      "north": false,
      "south": true,
      "waterlogged": false,
      "west": true
    },
    "15296": {
      "east": true,
      "north": false,
      "south": true,
      "waterlogged": false,
      "west": false
    },
    "15297": {
      "east": true,
      "north": false,
      "south": false,
      "waterlogged": true,
      "west": true
    },
    "15298": {
      "east": true,
      "north": false,
      "south": false,
      "waterlogged": true,
      "west": false
    },
    "15299": {
      "east": true,
      "north": false,
      "south": false,
      "waterlogged": false,
      "west": true
    },
    "15300": {
      "east": true,
      "north": false,
      "south": false,
      "waterlogged": false,
      "west": false
    },
    "15301": {
      "east": false,
      "north": true,
      "south": true,
      "waterlogged": true,
      "west": true
    },
    "15302": {
      "east": false,
      "north": true,
      "south": true,
      "waterlogged": true,
      "west": false
    },
    "15303": {
      "east": false,
      "north": true,
      "south": true,
      "waterlogged": false,
      "west": true
    },
    "15304": {
      "east": false,
      "north": true,
      "south": true,
      "waterlogged": false,
      "west": false
    },
    "15305": {
      "east": false,
      "north": true,
      "south": false,
      "waterlogged": true,
      "west": true
    },
    "15306": {
      "east": false,
      "north": true,
      "south": false,
      "waterlogged": true,
      "west": false
    },
    "15307": {
      "east": false,
      "north": true,
      "south": false,
      "waterlogged": false,
      "west": true
    },
    "15308": {
      "east": false,
      "north": true,
      "south": false,
      "waterlogged": false,
      "west": false
    },
    "15309": {
      "east": false,
      "north": false,
      "south": true,
      "waterlogged": true,
      "west": true
    },
    "15310": {
      "east": false,
      "north": false,
      "south": true,
      "waterlogged": true,
      "west": false
    },
    "15311": {
      "east": false,
      "north": false,
      "south": true,
      "waterlogged": false,
      "west": true
    },
    "15312": {
      "east": false,
      "north": false,
      "south": true,
      "waterlogged": false,
      "west": false
    },
    "15313": {
      "east": false,
      "north": false,
      "south": false,
      "waterlogged": true,
      "west": true
    },
    "15314": {
      "east": false,
      "north": false,
      "south": false,
      "waterlogged": true,
      "west": false
    },
    "15315": {
      "east": false,
      "north": false,
      "south": false,
      "waterlogged": false,
      "west": true
    },
    "15316": {
      "east": false,
      "north": false,
      "south": false,
      "waterlogged": false,
      "west": false
    }
  }
}