{
  "properties": {
    "facing": [
      "north",
      "east",
      "south",
      "west"
    ],
    "in_wall": [
      true,
      false
    ],
    "open": [
      true,
      false
    ],
    "powered": [
      true,
      false
    ]
  },
  "states": {
    "default": 5895,
    "5888": {
      "facing": "north",
      "in_wall": true,
      "open": true,
      "powered": true
    },
    "5889": {
      "facing": "north",
      "in_wall": true,
      "open": true,
      "powered": false
    },
    "5890": {
      "facing": "north",
      "in_wall": true,
      "open": false,
      "powered": true
    },
    "5891": {
      "facing": "north",
      "in_wall": true,
      "open": false,
      "powered": false
    },
    "5892": {
      "facing": "north",
      "in_wall": false,
      "open": true,
      "powered": true
    },
    "5893": {
      "facing": "north",
      "in_wall": false,
      "open": true,
      "powered": false
    },
    "5894": {
      "facing": "north",
      "in_wall": false,
      "open": false,
      "powered": true
    },
    "5895": {
      "facing": "north",
      "in_wall": false,
      "open": false,
      "powered": false
    },
    "5896": {
      "facing": "east",
      "in_wall": true,
      "open": true,
      "powered": true
    },
    "5897": {
      "facing": "east",
      "in_wall": true,
      "open": true,
      "powered": false
    },
    "5898": {
      "facing": "east",
      "in_wall": true,
      "open": false,
      "powered": true
    },
    "5899": {
      "facing": "east",
      "in_wall": true,
      "open": false,
      "powered": false
    },
    "5900": {
      "facing": "east",
      "in_wall": false,
      "open": true,
      "powered": true
    },
    "5901": {
      "facing": "east",
      "in_wall": false,
      "open": true,
      "powered": false
    },
    "5902": {
      "facing": "east",
      "in_wall": false,
      "open": false,
      "powered": true
    },
    "5903": {
      "facing": "east",
      "in_wall": false,
      "open": false,
      "powered": false
    },
    "5904": {
      "facing": "south",
      "in_wall": true,
      "open": true,
      "powered": true
    },
    "5905": {
      "facing": "south",
      "in_wall": true,
      "open": true,
      "powered": false
    },
    "5906": {
      "facing": "south",
      "in_wall": true,
      "open": false,
      "powered": true
    },
    "5907": {
      "facing": "south",
      "in_wall": true,
      "open": false,
      "powered": false
    },
    "5908": {
      "facing": "south",
      "in_wall": false,
      "open": true,
      "powered": true
    },
    "5909": {
      "facing": "south",
      "in_wall": false,
      "open": true,
      "powered": false
    },
    "5910": {
      "facing": "south",
      "in_wall": false,
      "open": false,
      "powered": true
    },
    "5911": {
      "facing": "south",
      "in_wall": false,
      "open": false,
      "powered": false
    },
    "5912": {
      "facing": "west",
      "in_wall": true,
      "open": true,
      "powered": true
    },
    "5913": {
      "facing": "west",
      "in_wall": true,
      "open": true,
      "powered": false
    },
    "5914": {
      "facing": "west",
      "in_wall": true,
      "open": false,
      "powered": true
    },
    "5915": {
      "facing": "west",
      "in_wall": true,
      "open": false,
      "powered": false
    },
    "5916": {
      "facing": "west",
      "in_wall": false,
      "open": true,
      "powered": true
    },
    "5917": {
      "facing": "west",
      "in_wall": false,
      "open": true,
      "powered": false
    },
    "5918": {
      "facing": "west",
      "in_wall": false,
      "open": false,
      "powered": true
    },
    "5919": {
      "facing": "west",
      "in_wall": false,
      "open": false,
      "powered": false
    }
  }
}