{
  "properties": {
    "east": [
      true,
      false
    ],
    "north": [
      true,
      false
    ],
    "south": [
      true,
      false
    ],
    "waterlogged": [
      true,
      false
    ],
    "west": [
      true,
      false
    ]
  },
  "states": {
    "7433": {
      "east": true,
      "north": true,
      "south": true,
      "waterlogged": true,
      "west": true
    },
    "7434": {
      "east": true,
      "north": true,
      "south": true,
      "waterlogged": true,
      "west": false
    },
    "7435": {
      "east": true,
      "north": true,
      "south": true,
      "waterlogged": false,
      "west": true
    },
    "7436": {
      "east": true,
      "north": true,
      "south": true,
      "waterlogged": false,
      "west": false
    },
    "7437": {
      "east": true,
      "north": true,
      "south": false,
      "waterlogged": true,
      "west": true
    },
    "7438": {
      "east": true,
      "north": true,
      "south": false,
      "waterlogged": true,
      "west": false
    },
    "7439": {
      "east": true,
      "north": true,
      "south": false,
      "waterlogged": false,
      "west": true
    },
    "7440": {
      "east": true,
      "north": true,
      "south": false,
      "waterlogged": false,
      "west": false
    },
    "7441": {
      "east": true,
      "north": false,
      "south": true,
      "waterlogged": true,
      "west": true
    },
    "7442": {
      "east": true,
      "north": false,
      "south": true,
      "waterlogged": true,
      "west": false
    },
    "7443": {
      "east": true,
      "north": false,
      "south": true,
      "waterlogged": false,
      "west": true
    },
    "7444": {
      "east": true,
      "north": false,
      "south": true,
      "waterlogged": false,
      "west": false
    },
    "7445": {
      "east": true,
      "north": false,
      "south": false,
      "waterlogged": true,
      "west": true
    },
    "7446": {
      "east": true,
      "north": false,
      "south": false,
      "waterlogged": true,
      "west": false
    },
    "7447": {
      "east": true,
      "north": false,
      "south": false,
      "waterlogged": false,
      "west": true
    },
    "7448": {
      "east": true,
      "north": false,
      "south": false,
      "waterlogged": false,
      "west": false
    },
    "7449": {
      "east": false,
      "north": true,
      "south": true,
      "waterlogged": true,
      "west": true
    },
    "7450": {
      "east": false,
      "north": true,
      "south": true,
      "waterlogged": true,
      "west": false
    },
    "7451": {
      "east": false,
      "north": true,
      "south": true,
      "waterlogged": false,
      "west": true
    },
    "7452": {
      "east": false,
      "north": true,
      "south": true,
      "waterlogged": false,
      "west": false
    },
    "7453": {
      "east": false,
      "north": true,
      "south": false,
      "waterlogged": true,
      "west": true
    },
    "7454": {
      "east": false,
      "north": true,
      "south": false,
      "waterlogged": true,
      "west": false
    },
    "7455": {
      "east": false,
      "north": true,
      "south": false,
      "waterlogged": false,
      "west": true
    },
    "7456": {
      "east": false,
      "north": true,
      "south": false,
      "waterlogged": false,
      "west": false
    },
    "7457": {
      "east": false,
      "north": false,
      "south": true,
      "waterlogged": true,
      "west": true
    },
    "7458": {
      "east": false,
      "north": false,
      "south": true,
      "waterlogged": true,
      "west": false
    },
    "7459": {
      "east": false,
      "north": false,
      "south": true,
      "waterlogged": false,
      "west": true
    },
    "7460": {
      "east": false,
      "north": false,
      "south": true,
      "waterlogged": false,
      "west": false
    },
    "7461": {
      "east": false,
      "north": false,
      "south": false,
      "waterlogged": true,
      "west": true
    },
    "7462": {
      "east": false,
      "north": false,
      "south": false,
      "waterlogged": true,
      "west": false
    },
    "7463": {
      "east": false,
      "north": false,
      "south": false,
      "waterlogged": false,
      "west": true
    },
    "7464": {
      "east": false,
      "north": false,
      "south": false,
      "waterlogged": false,
      "west": false
    }
  }
}