{
  "properties": {
    "facing": [
      "north",
      "south",
      "west",
      "east"
    ],
    "half": [
      "top",
      "bottom"
    ],
    "open": [
      true,
      false
    ],
    "powered": [
      true,
      false
    ],
    "waterlogged": [
      true,
      false
    ]
  },
  "states": {
    "default": 3929,
    "3914": {
      "facing": "north",
      "half": "top",
      "open": true,
      "powered": true,
      "waterlogged": true
    },
    "3915": {
      "facing": "north",
      "half": "top",
      "open": true,
      "powered": true,
      "waterlogged": false
    },
    "3916": {
      "facing": "north",
      "half": "top",
      "open": true,
      "powered": false,
      "waterlogged": true
    },
    "3917": {
      "facing": "north",
      "half": "top",
      "open": true,
      "powered": false,
      "waterlogged": false
    },
    "3918": {
      "facing": "north",
      "half": "top",
      "open": false,
      "powered": true,
      "waterlogged": true
    },
    "3919": {
      "facing": "north",
      "half": "top",
      "open": false,
      "powered": true,
      "waterlogged": false
    },
    "3920": {
      "facing": "north",
      "half": "top",
      "open": false,
      "powered": false,
      "waterlogged": true
    },
    "3921": {
      "facing": "north",
      "half": "top",
      "open": false,
      "powered": false,
      "waterlogged": false
    },
    "3922": {
      "facing": "north",
      "half": "bottom",
      "open": true,
      "powered": true,
      "waterlogged": true
    },
    "3923": {
      "facing": "north",
      "half": "bottom",
      "open": true,
      "powered": true,
      "waterlogged": false
    },
    "3924": {
      "facing": "north",
      "half": "bottom",
      "open": true,
      "powered": false,
      "waterlogged": true
    },
    "3925": {
      "facing": "north",
      "half": "bottom",
      "open": true,
      "powered": false,
      "waterlogged": false
    },
    "3926": {
      "facing": "north",
      "half": "bottom",
      "open": false,
      "powered": true,
      "waterlogged": true
    },
    "3927": {
      "facing": "north",
      "half": "bottom",
      "open": false,
      "powered": true,
      "waterlogged": false
    },
    "3928": {
      "facing": "north",
      "half": "bottom",
      "open": false,
      "powered": false,
      "waterlogged": true
    },
    "3929": {
      "facing": "north",
      "half": "bottom",
      "open": false,
      "powered": false,
      "waterlogged": false
    },
    "3930": {
      "facing": "south",
      "half": "top",
      "open": true,
      "powered": true,
      "waterlogged": true
    },
    "3931": {
      "facing": "south",
      "half": "top",
      "open": true,
      "powered": true,
      "waterlogged": false
    },
    "3932": {
      "facing": "south",
      "half": "top",
      "open": true,
      "powered": false,
      "waterlogged": true
    },
    "3933": {
      "facing": "south",
      "half": "top",
      "open": true,
      "powered": false,
      "waterlogged": false
    },
    "3934": {
      "facing": "south",
      "half": "top",
      "open": false,
      "powered": true,
      "waterlogged": true
    },
    "3935": {
      "facing": "south",
      "half": "top",
      "open": false,
      "powered": true,
      "waterlogged": false
    },
    "3936": {
      "facing": "south",
      "half": "top",
      "open": false,
      "powered": false,
      "waterlogged": true
    },
    "3937": {
      "facing": "south",
      "half": "top",
      "open": false,
      "powered": false,
      "waterlogged": false
    },
    "3938": {
      "facing": "south",
      "half": "bottom",
      "open": true,
      "powered": true,
      "waterlogged": true
    },
    "3939": {
      "facing": "south",
      "half": "bottom",
      "open": true,
      "powered": true,
      "waterlogged": false
    },
    "3940": {
      "facing": "south",
      "half": "bottom",
      "open": true,
      "powered": false,
      "waterlogged": true
    },
    "3941": {
      "facing": "south",
      "half": "bottom",
      "open": true,
      "powered": false,
      "waterlogged": false
    },
    "3942": {
      "facing": "south",
      "half": "bottom",
      "open": false,
      "powered": true,
      "waterlogged": true
    },
    "3943": {
      "facing": "south",
      "half": "bottom",
      "open": false,
      "powered": true,
      "waterlogged": false
    },
    "3944": {
      "facing": "south",
      "half": "bottom",
      "open": false,
      "powered": false,
      "waterlogged": true
    },
    "3945": {
      "facing": "south",
      "half": "bottom",
      "open": false,
      "powered": false,
      "waterlogged": false
    },
    "3946": {
      "facing": "west",
      "half": "top",
      "open": true,
      "powered": true,
      "waterlogged": true
    },
    "3947": {
      "facing": "west",
      "half": "top",
      "open": true,
      "powered": true,
      "waterlogged": false
    },
    "3948": {
      "facing": "west",
      "half": "top",
      "open": true,
      "powered": false,
      "waterlogged": true
    },
    "3949": {
      "facing": "west",
      "half": "top",
      "open": true,
      "powered": false,
      "waterlogged": false
    },
    "3950": {
      "facing": "west",
      "half": "top",
      "open": false,
      "powered": true,
      "waterlogged": true
    },
    "3951": {
      "facing": "west",
      "half": "top",
      "open": false,
      "powered": true,
      "waterlogged": false
    },
    "3952": {
      "facing": "west",
      "half": "top",
      "open": false,
      "powered": false,
      "waterlogged": true
    },
    "3953": {
      "facing": "west",
      "half": "top",
      "open": false,
      "powered": false,
      "waterlogged": false
    },
    "3954": {
      "facing": "west",
      "half": "bottom",
      "open": true,
      "powered": true,
      "waterlogged": true
    },
    "3955": {
      "facing": "west",
      "half": "bottom",
      "open": true,
      "powered": true,
      "waterlogged": false
    },
    "3956": {
      "facing": "west",
      "half": "bottom",
      "open": true,
      "powered": false,
      "waterlogged": true
    },
    "3957": {
      "facing": "west",
      "half": "bottom",
      "open": true,
      "powered": false,
      "waterlogged": false
    },
    "3958": {
      "facing": "west",
      "half": "bottom",
      "open": false,
      "powered": true,
      "waterlogged": true
    },
    "3959": {
      "facing": "west",
      "half": "bottom",
      "open": false,
      "powered": true,
      "waterlogged": false
    },
    "3960": {
      "facing": "west",
      "half": "bottom",
      "open": false,
      "powered": false,
      "waterlogged": true
    },
    "3961": {
      "facing": "west",
      "half": "bottom",
      "open": false,
      "powered": false,
      "waterlogged": false
    },
    "3962": {
      "facing": "east",
      "half": "top",
      "open": true,
      "powered": true,
      "waterlogged": true
    },
    "3963": {
      "facing": "east",
      "half": "top",
      "open": true,
      "powered": true,
      "waterlogged": false
    },
    "3964": {
      "facing": "east",
      "half": "top",
      "open": true,
      "powered": false,
      "waterlogged": true
    },
    "3965": {
      "facing": "east",
      "half": "top",
      "open": true,
      "powered": false,
      "waterlogged": false
    },
    "3966": {
      "facing": "east",
      "half": "top",
      "open": false,
      "powered": true,
      "waterlogged": true
    },
    "3967": {
      "facing": "east",
      "half": "top",
      "open": false,
      "powered": true,
      "waterlogged": false
    },
    "3968": {
      "facing": "east",
      "half": "top",
      "open": false,
      "powered": false,
      "waterlogged": true
    },
    "3969": {
      "facing": "east",
      "half": "top",
      "open": false,
      "powered": false,
      "waterlogged": false
    },
    "3970": {
      "facing": "east",
      "half": "bottom",
      "open": true,
      "powered": true,
      "waterlogged": true
    },
    "3971": {
      "facing": "east",
      "half": "bottom",
      "open": true,
      "powered": true,
      "waterlogged": false
    },
    "3972": {
      "facing": "east",
      "half": "bottom",
      "open": true,
      "powered": false,
      "waterlogged": true
    },
    "3973": {
      "facing": "east",
      "half": "bottom",
      "open": true,
      "powered": false,
      "waterlogged": false
    },
    "3974": {
      "facing": "east",
      "half": "bottom",
      "open": false,
      "powered": true,
      "waterlogged": true
    },
    "3975": {
      "facing": "east",
      "half": "bottom",
      "open": false,
      "powered": true,
      "waterlogged": false
    },
    "3976": {
      "facing": "east",
      "half": "bottom",
      "open": false,
      "powered": false,
      "waterlogged": true
    },
    "3977": {
      "facing": "east",
      "half": "bottom",
      "open": false,
      "powered": false,
      "waterlogged": false
    }
  }
}