{
  "properties": {
    "facing": [
      "north",
      "south",
      "west",
      "east"
    ],
    "half": [
      "upper",
      "lower"
    ],
    "hinge": [
      "left",
      "right"
    ],
    "open": [
      true,
      false
    ],
    "powered": [
      true,
      false
    ]
  },
  "states": {
    "default": 15824,
    "15813": {
      "facing": "north",
      "half": "upper",
      "hinge": "left",
      "open": true,
      "powered": true
    },
    "15814": {
      "facing": "north",
      "half": "upper",
      "hinge": "left",
      "open": true,
      "powered": false
    },
    "15815": {
      "facing": "north",
      "half": "upper",
      "hinge": "left",
      "open": false,
      "powered": true
    },
    "15816": {
      "facing": "north",
      "half": "upper",
      "hinge": "left",
      "open": false,
      "powered": false
    },
    "15817": {
      "facing": "north",
      "half": "upper",
      "hinge": "right",
      "open": true,
      "powered": true
    },
    "15818": {
      "facing": "north",
      "half": "upper",
      "hinge": "right",
      "open": true,
      "powered": false
    },
    "15819": {
      "facing": "north",
      "half": "upper",
      "hinge": "right",
      "open": false,
      "powered": true
    },
    "15820": {
      "facing": "north",
      "half": "upper",
      "hinge": "right",
      "open": false,
      "powered": false
    },
    "15821": {
      "facing": "north",
      "half": "lower",
      "hinge": "left",
      "open": true,
      "powered": true
    },
    "15822": {
      "facing": "north",
      "half": "lower",
      "hinge": "left",
      "open": true,
      "powered": false
    },
    "15823": {
      "facing": "north",
      "half": "lower",
      "hinge": "left",
      "open": false,
      "powered": true
    },
    "15824": {
      "facing": "north",
      "half": "lower",
      "hinge": "left",
      "open": false,
      "powered": false
    },
    "15825": {
      "facing": "north",
      "half": "lower",
      "hinge": "right",
      "open": true,
      "powered": true
    },
    "15826": {
      "facing": "north",
      "half": "lower",
      "hinge": "right",
      "open": true,
      "powered": false
    },
    "15827": {
      "facing": "north",
      "half": "lower",
      "hinge": "right",
      "open": false,
      "powered": true
    },
    "15828": {
      "facing": "north",
      "half": "lower",
      "hinge": "right",
      "open": false,
      "powered": false
    },
    "15829": {
      "facing": "south",
      "half": "upper",
      "hinge": "left",
      "open": true,
      "powered": true
    },
    "15830": {
      "facing": "south",
      "half": "upper",
      "hinge": "left",
      "open": true,
      "powered": false
    },
    "15831": {
      "facing": "south",
      "half": "upper",
      "hinge": "left",
      "open": false,
      "powered": true
    },
    "15832": {
      "facing": "south",
      "half": "upper",
      "hinge": "left",
      "open": false,
      "powered": false
    },
    "15833": {
      "facing": "south",
      "half": "upper",
      "hinge": "right",
      "open": true,
      "powered": true
    },
    "15834": {
      "facing": "south",
      "half": "upper",
      "hinge": "right",
      "open": true,
      "powered": false
    },
    "15835": {
      "facing": "south",
      "half": "upper",
      "hinge": "right",
      "open": false,
      "powered": true
    },
    "15836": {
      "facing": "south",
      "half": "upper",
      "hinge": "right",
      "open": false,
      "powered": false
    },
    "15837": {
      "facing": "south",
      "half": "lower",
      "hinge": "left",
      "open": true,
      "powered": true
    },
    "15838": {
      "facing": "south",
      "half": "lower",
      "hinge": "left",
      "open": true,
      "powered": false
    },
    "15839": {
      "facing": "south",
      "half": "lower",
      "hinge": "left",
      "open": false,
      "powered": true
    },
    "15840": {
      "facing": "south",
      "half": "lower",
      "hinge": "left",
      "open": false,
      "powered": false
    },
    "15841": {
      "facing": "south",
      "half": "lower",
      "hinge": "right",
      "open": true,
      "powered": true
    },
    "15842": {
      "facing": "south",
      "half": "lower",
      "hinge": "right",
      "open": true,
      "powered": false
    },
    "15843": {
      "facing": "south",
      "half": "lower",
      "hinge": "right",
      "open": false,
      "powered": true
    },
    "15844": {
      "facing": "south",
      "half": "lower",
      "hinge": "right",
      "open": false,
      "powered": false
    },
    "15845": {
      "facing": "west",
      "half": "upper",
      "hinge": "left",
      "open": true,
      "powered": true
    },
    "15846": {
      "facing": "west",
      "half": "upper",
      "hinge": "left",
      "open": true,
      "powered": false
    },
    "15847": {
      "facing": "west",
      "half": "upper",
      "hinge": "left",
      "open": false,
      "powered": true
    },
    "15848": {
      "facing": "west",
      "half": "upper",
      "hinge": "left",
      "open": false,
      "powered": false
    },
    "15849": {
      "facing": "west",
      "half": "upper",
      "hinge": "right",
      "open": true,
      "powered": true
    },
    "15850": {
      "facing": "west",
      "half": "upper",
      "hinge": "right",
      "open": true,
      "powered": false
    },
    "15851": {
      "facing": "west",
      "half": "upper",
      "hinge": "right",
      "open": false,
      "powered": true
    },
    "15852": {
      "facing": "west",
      "half": "upper",
      "hinge": "right",
      "open": false,
      "powered": false
    },
    "15853": {
      "facing": "west",
      "half": "lower",
      "hinge": "left",
      "open": true,
      "powered": true
    },
    "15854": {
      "facing": "west",
      "half": "lower",
      "hinge": "left",
      "open": true,
      "powered": false
    },
    "15855": {
      "facing": "west",
      "half": "lower",
      "hinge": "left",
      "open": false,
      "powered": true
    },
    "15856": {
      "facing": "west",
      "half": "lower",
      "hinge": "left",
      "open": false,
      "powered": false
    },
    "15857": {
      "facing": "west",
      "half": "lower",
      "hinge": "right",
      "open": true,
      "powered": true
    },
    "15858": {
      "facing": "west",
      "half": "lower",
      "hinge": "right",
      "open": true,
      "powered": false
    },
    "15859": {
      "facing": "west",
      "half": "lower",
      "hinge": "right",
      "open": false,
      "powered": true
    },
    "15860": {
      "facing": "west",
      "half": "lower",
      "hinge": "right",
      "open": false,
      "powered": false
    },
    "15861": {
      "facing": "east",
      "half": "upper",
      "hinge": "left",
      "open": true,
      "powered": true
    },
    "15862": {
      "facing": "east",
      "half": "upper",
      "hinge": "left",
      "open": true,
      "powered": false
    },
    "15863": {
      "facing": "east",
      "half": "upper",
      "hinge": "left",
      "open": false,
      "powered": true
    },
    "15864": {
      "facing": "east",
      "half": "upper",
      "hinge": "left",
      "open": false,
      "powered": false
    },
    "15865": {
      "facing": "east",
      "half": "upper",
      "hinge": "right",
      "open": true,
      "powered": true
    },
    "15866": {
      "facing": "east",
      "half": "upper",
      "hinge": "right",
      "open": true,
      "powered": false
    },
    "15867": {
      "facing": "east",
      "half": "upper",
      "hinge": "right",
      "open": false,
      "powered": true
    },
    "15868": {
      "facing": "east",
      "half": "upper",
      "hinge": "right",
      "open": false,
      "powered": false
    },
    "15869": {
      "facing": "east",
      "half": "lower",
      "hinge": "left",
      "open": true,
      "powered": true
    },
    "15870": {
      "facing": "east",
      "half": "lower",
      "hinge": "left",
      "open": true,
      "powered": false
    },
    "15871": {
      "facing": "east",
      "half": "lower",
      "hinge": "left",
      "open": false,
      "powered": true
    },
    "15872": {
      "facing": "east",
      "half": "lower",
      "hinge": "left",
      "open": false,
      "powered": false
    },
    "15873": {
      "facing": "east",
      "half": "lower",
      "hinge": "right",
      "open": true,
      "powered": true
    },
    "15874": {
      "facing": "east",
      "half": "lower",
      "hinge": "right",
      "open": true,
      "powered": false
    },
    "15875": {
      "facing": "east",
      "half": "lower",
      "hinge": "right",
      "open": false,
      "powered": true
    },
    "15876": {
      "facing": "east",
      "half": "lower",
      "hinge": "right",
      "open": false,
      "powered": false
    }
  }
}