{
  "properties": {
    "east": [
      true,
      false
    ],
    "north": [
      true,
      false
    ],
    "south": [
      true,
      false
    ],
    "west": [
      true,
      false
    ]
  },
  "states": {
    "default": 5005,
    "4990": {
      "east": true,
      "north": true,
      "south": true,
      "west": true
    },
    "4991": {
      "east": true,
      "north": true,
      "south": true,
      "west": false
    },
    "4992": {
      "east": true,
      "north": true,
      "south": false,
      "west": true
    },
    "4993": {
      "east": true,
      "north": true,
      "south": false,
      "west": false
    },
    "4994": {
      "east": true,
      "north": false,
      "south": true,
      "west": true
    },
    "4995": {
      "east": true,
      "north": false,
      "south": true,
      "west": false
    },
    "4996": {
      "east": true,
      "north": false,
      "south": false,
      "west": true
    },
    "4997": {
      "east": true,
      "north": false,
      "south": false,
      "west": false
    },
    "4998": {
      "east": false,
      "north": true,
      "south": true,
      "west": true
    },
    "4999": {
      "east": false,
      "north": true,
      "south": true,
      "west": false
    },
    "5000": {
      "east": false,
      "north": true,
      "south": false,
      "west": true
    },
    "5001": {
      "east": false,
      "north": true,
      "south": false,
      "west": false
    },
    "5002": {
      "east": false,
      "north": false,
      "south": true,
      "west": true
    },
    "5003": {
      "east": false,
      "north": false,
      "south": true,
      "west": false
    },
    "5004": {
      "east": false,
      "north": false,
      "south": false,
      "west": true
    },
    "5005": {
      "east": false,
      "north": false,
      "south": false,
      "west": false
    }
  }
}